pysimdb/__init__.py
pysimdb/database.py
pysimdb/query_builder.py
pysimdb/schema.py
pysimdb/storage.py
pysimdb-0.1.15.dist-info/licenses/LICENSE
pysimdb-0.1.15.dist-info/METADATA
pysimdb-0.1.15.dist-info/WHEEL
pysimdb-0.1.15.dist-info/top_level.txt
pysimdb-0.1.15.dist-info/RECORD
