Metadata-Version: 2.4
Name: pysimdb
Version: 0.1.15
Summary: A lightweight, JSON-based database library for Python
Home-page: https://github.com/shayanheidari01/pysimdb
Author: Shayan Heidari
Author-email: Shayan Heidari <shayanheidari01@gmail.com>
License:                     GNU GENERAL PUBLIC LICENSE
Project-URL: Homepage, https://github.com/shayanheidari01/pysimdb
Project-URL: Bug Tracker, https://github.com/shayanheidari01/pysimdb/issues
Project-URL: Documentation, https://github.com/shayanheidari01/pysimdb#readme
Project-URL: Source Code, https://github.com/shayanheidari01/pysimdb
Classifier: Development Status :: 4 - Beta
Classifier: Intended Audience :: Developers
Classifier: License :: OSI Approved :: GNU General Public License v3 (GPLv3)
Classifier: Operating System :: OS Independent
Classifier: Programming Language :: Python :: 3
Classifier: Programming Language :: Python :: 3.6
Classifier: Programming Language :: Python :: 3.7
Classifier: Programming Language :: Python :: 3.8
Classifier: Programming Language :: Python :: 3.9
Classifier: Programming Language :: Python :: 3.10
Classifier: Programming Language :: Python :: 3.11
Classifier: Topic :: Database
Classifier: Topic :: Software Development :: Libraries :: Python Modules
Requires-Python: >=3.6
License-File: LICENSE
Requires-Dist: pysimdjson>=5.0.0
Provides-Extra: dev
Requires-Dist: pytest>=6.0; extra == "dev"
Requires-Dist: black; extra == "dev"
Requires-Dist: flake8; extra == "dev"
Dynamic: author
Dynamic: home-page
Dynamic: license-file
Dynamic: requires-python
